[
  {
    "productId": 8065577198,
    "productName": "2025 하기스 맥스드라이 에어팬티 대형 공용 1팩, 4단계, 48매",
    "productPrice": 27040,
    "productImage": "https://thumbnail.coupangcdn.com/thumbnails/remote/657x657q90trim/image/vendor_inventory/7f56/5ec826ce5feaffe2533a346183caddcac0ce684895378cc91b01b8a5e600.jpg",
    "productUrl": "https://www.coupang.com/vp/products/8065577198?itemId=25589675117&vendorItemId=92580493830&q=%ED%95%98%EA%B8%B0%EC%8A%A4%20%EB%A7%A5%EC%8A%A4%EB%93%9C%EB%9D%BC%EC%9D%B4%20%ED%8C%AC%ED%8B%B0%204%EB%8B%A8%EA%B3%84&searchId=7e8f4b708865965&sourceType=search&itemsCount=72&searchRank=0&rank=0"
  },
  {
    "productId": 8750574165,
    "productName": "하기스 2025 맥스드라이 에어 팬티형 기저귀 남여공용, 4단계, 48매",
    "productPrice": 27080,
    "productImage": "https://thumbnail.coupangcdn.com/thumbnails/remote/657x657q90trim/image/vendor_inventory/05d9/3c0c19000a0bbd608f18837ea582123626fa5bfd6851dd31dc264ea80a1e.jpg",
    "productUrl": "https://www.coupang.com/vp/products/8750574165?itemId=25295831640&vendorItemId=93819572390&q=%ED%95%98%EA%B8%B0%EC%8A%A4%20%EB%A7%A5%EC%8A%A4%EB%93%9C%EB%9D%BC%EC%9D%B4%20%ED%8C%AC%ED%8B%B0%204%EB%8B%A8%EA%B3%84&searchId=7e8f4b708865965&sourceType=search&itemsCount=72&searchRank=1&rank=1"
  },
  {
    "productId": 9335100743,
    "productName": "하기스 2024 맥스드라이 팬티형 기저귀 남여공용 소형 4~8kg, 4단계, 42매",
    "productPrice": 28120,
    "productImage": "https://thumbnail.coupangcdn.com/thumbnails/remote/657x657q90trim/image/vendor_inventory/4a00/8604728496cd33bedca23eb2da357a8681e43ba1a24ed3a2ab8bf4b86290.png",
    "productUrl": "https://www.coupang.com/vp/products/9335100743?itemId=23950410933&vendorItemId=90972118800&q=%ED%95%98%EA%B8%B0%EC%8A%A4%20%EB%A7%A5%EC%8A%A4%EB%93%9C%EB%9D%BC%EC%9D%B4%20%ED%8C%AC%ED%8B%B0%204%EB%8B%A8%EA%B3%84&searchId=7e8f4b708865965&sourceType=search&itemsCount=72&searchRank=2&rank=2"
  },
  {
    "productId": 9041962923,
    "productName": "하기스 NEW 맥스드라이 여아용 팬티형 기저귀, 4단계, 52매",
    "productPrice": 28500,
    "productImage": "https://thumbnail.coupangcdn.com/thumbnails/remote/657x657q90trim/image/vendor_inventory/17e9/0238fae98452a45d4b1b4419ebaf1a2c10f8b22ad1c3d705c5d40b061e7b.jpg",
    "productUrl": "https://www.coupang.com/vp/products/9041962923?itemId=27727218451&vendorItemId=94688533224&q=%ED%95%98%EA%B8%B0%EC%8A%A4%20%EB%A7%A5%EC%8A%A4%EB%93%9C%EB%9D%BC%EC%9D%B4%20%ED%8C%AC%ED%8B%B0%204%EB%8B%A8%EA%B3%84&searchId=7e8f4b708865965&sourceType=search&itemsCount=72&searchRank=3&rank=3"
  },
  {
    "productId": 7927695903,
    "productName": "하기스 2025 맥스드라이 팬티형 기저귀 남아용 대형, 4단계, 52매",
    "productPrice": 29900,
    "productImage": "https://thumbnail.coupangcdn.com/thumbnails/remote/657x657q90trim/image/vendor_inventory/0dd9/5405fe3f141cf6b86066e6cd421fab832b094e89333f86e26ad83b563828.jpg",
    "productUrl": "https://www.coupang.com/vp/products/7927695903?itemId=27127608024&vendorItemId=94274958943&q=%ED%95%98%EA%B8%B0%EC%8A%A4%20%EB%A7%A5%EC%8A%A4%EB%93%9C%EB%9D%BC%EC%9D%B4%20%ED%8C%AC%ED%8B%B0%204%EB%8B%A8%EA%B3%84&searchId=7e8f4b708865965&sourceType=search&itemsCount=72&searchRank=5&rank=5"
  },
  {
    "productId": 7273646569,
    "productName": "하기스 NEW 맥스드라이 여아용 팬티형 기저귀, 4단계, 52매",
    "productPrice": 31400,
    "productImage": "https://thumbnail.coupangcdn.com/thumbnails/remote/657x657q90trim/image/vendor_inventory/63b5/fb5c5362b83f016703133affdc0971e8bd8de2658b330d966809c8b72e07.jpg",
    "productUrl": "https://www.coupang.com/vp/products/7273646569?itemId=23107316637&vendorItemId=94002273273&q=%ED%95%98%EA%B8%B0%EC%8A%A4%20%EB%A7%A5%EC%8A%A4%EB%93%9C%EB%9D%BC%EC%9D%B4%20%ED%8C%AC%ED%8B%B0%204%EB%8B%A8%EA%B3%84&searchId=7e8f4b708865965&sourceType=search&itemsCount=72&searchRank=6&rank=6"
  },
  {
    "productId": 9314180211,
    "productName": "하기스 2021 신형 맥스드라이 기저귀 점보형 6단계(14~19kg) 팬티형 아동공용, 4단계, 42매",
    "productPrice": 34500,
    "productImage": "https://thumbnail.coupangcdn.com/thumbnails/remote/657x657q90trim/image/vendor_inventory/c530/35e09c3a016c4baf4be4c61ae673642bcdfee4bfc2cc399fa6bd1e1b8816.png",
    "productUrl": "https://www.coupang.com/vp/products/9314180211?itemId=27191704610&vendorItemId=94159205761&q=%ED%95%98%EA%B8%B0%EC%8A%A4%20%EB%A7%A5%EC%8A%A4%EB%93%9C%EB%9D%BC%EC%9D%B4%20%ED%8C%AC%ED%8B%B0%204%EB%8B%A8%EA%B3%84&searchId=7e8f4b708865965&sourceType=search&itemsCount=72&searchRank=7&rank=7"
  },
  {
    "productId": 9190626750,
    "productName": "하기스 맥스드라이 팬티형 기저귀 여아용 대형 4단계(10~14kg)",
    "productPrice": 34500,
    "productImage": "https://thumbnail.coupangcdn.com/thumbnails/remote/657x657q90trim/image/vendor_inventory/298f/11a6a43007d7e922ed89e49d70dc3f9a3d6fb6d10ff3181ddadeed77fdcb.png",
    "productUrl": "https://www.coupang.com/vp/products/9190626750?itemId=27135850871&vendorItemId=94103792941&q=%ED%95%98%EA%B8%B0%EC%8A%A4%20%EB%A7%A5%EC%8A%A4%EB%93%9C%EB%9D%BC%EC%9D%B4%20%ED%8C%AC%ED%8B%B0%204%EB%8B%A8%EA%B3%84&searchId=7e8f4b708865965&sourceType=search&itemsCount=72&searchRank=8&rank=8"
  },
  {
    "productId": 7685706619,
    "productName": "하기스 하기스 맥스드라이 팬티 4단계 공용 대형 42매",
    "productPrice": 55500,
    "productImage": "https://thumbnail.coupangcdn.com/thumbnails/remote/657x657q90trim/image/vendor_inventory/dd38/dc766bab9752ccd6005265dcbb8758daa0ddc180a07eca40f58a785b3ef1.jpg",
    "productUrl": "https://www.coupang.com/vp/products/7685706619?itemId=27819572297&vendorItemId=94798535405&q=%ED%95%98%EA%B8%B0%EC%8A%A4%20%EB%A7%A5%EC%8A%A4%EB%93%9C%EB%9D%BC%EC%9D%B4%20%ED%8C%AC%ED%8B%B0%204%EB%8B%A8%EA%B3%84&searchId=7e8f4b708865965&sourceType=search&itemsCount=72&searchRank=15&rank=15"
  },
  {
    "productId": 8750586885,
    "productName": "하기스 NEW 맥스드라이 팬티형 기저귀 여아용, 104개, 4단계",
    "productPrice": 65000,
    "productImage": "https://thumbnail.coupangcdn.com/thumbnails/remote/657x657q90trim/image/vendor_inventory/0c7b/ee3afe550ba3563b0f26d485807d3777a753a81cd49c0855222fde12394e.jpg",
    "productUrl": "https://www.coupang.com/vp/products/8750586885?itemId=27633436051&vendorItemId=88949780441&q=%ED%95%98%EA%B8%B0%EC%8A%A4%20%EB%A7%A5%EC%8A%A4%EB%93%9C%EB%9D%BC%EC%9D%B4%20%ED%8C%AC%ED%8B%B0%204%EB%8B%A8%EA%B3%84&searchId=7e8f4b708865965&sourceType=search&itemsCount=72&searchRank=20&rank=20"
  },
  {
    "productId": 8413424554,
    "productName": "하기스 2024 맥스드라이 팬티형 기저귀 여아용, 4단계, 104매",
    "productPrice": 63360,
    "productImage": "https://thumbnail.coupangcdn.com/thumbnails/remote/657x657q90trim/image/vendor_inventory/b38c/dd268f0142c248e58524a652fb49f18ac5d815f0a5c5e8b6d91fa0b0a6e0.png",
    "productUrl": "https://www.coupang.com/vp/products/8413424554?itemId=25427500732&vendorItemId=94295791342&q=%ED%95%98%EA%B8%B0%EC%8A%A4%20%EB%A7%A5%EC%8A%A4%EB%93%9C%EB%9D%BC%EC%9D%B4%20%ED%8C%AC%ED%8B%B0%204%EB%8B%A8%EA%B3%84&searchId=7e8f4b708865965&sourceType=search&itemsCount=72&searchRank=21&rank=21"
  },
  {
    "productId": 9141918901,
    "productName": "하기스 맥스드라이 팬티형 기저귀 여아용 대형 4단계(10~14kg), 대형(L)",
    "productPrice": 72500,
    "productImage": "https://thumbnail.coupangcdn.com/thumbnails/remote/657x657q90trim/image/vendor_inventory/211e/b241cdaa1b67954ca6f2e5cddc0c1657a0ee9da8eb5dcc8f3208e5d74fb7.png",
    "productUrl": "https://www.coupang.com/vp/products/9141918901?itemId=27120044222&vendorItemId=94364193463&q=%ED%95%98%EA%B8%B0%EC%8A%A4%20%EB%A7%A5%EC%8A%A4%EB%93%9C%EB%9D%BC%EC%9D%B4%20%ED%8C%AC%ED%8B%B0%204%EB%8B%A8%EA%B3%84&searchId=7e8f4b708865965&sourceType=search&itemsCount=72&searchRank=24&rank=24"
  },
  {
    "productId": 9370891878,
    "productName": "하기스 하기스 맥스드라이 팬티 4단계 남아 대형 52매",
    "productPrice": 114700,
    "productImage": "https://thumbnail.coupangcdn.com/thumbnails/remote/657x657q90trim/image/vendor_inventory/e725/26d31cee710a79e3942fc02d6fad6efd1d3284543d503dbda18bc304ce9c.jpg",
    "productUrl": "https://www.coupang.com/vp/products/9370891878?itemId=27591408780&vendorItemId=94787833694&q=%ED%95%98%EA%B8%B0%EC%8A%A4%20%EB%A7%A5%EC%8A%A4%EB%93%9C%EB%9D%BC%EC%9D%B4%20%ED%8C%AC%ED%8B%B0%204%EB%8B%A8%EA%B3%84&searchId=7e8f4b708865965&sourceType=search&itemsCount=72&searchRank=26&rank=26"
  },
  {
    "productId": 9358055613,
    "productName": "하기스 NEW 맥스드라이 팬티형 기저귀 남아용 대형 4단계(10~14kg), 4단계, 80매",
    "productPrice": 74900,
    "productImage": "https://thumbnail.coupangcdn.com/thumbnails/remote/657x657q90trim/image/vendor_inventory/ce66/ec9bc42e0b9cd216a69243d7e59ba891dc3fe06646ee16ca2876fac383a8.jpg",
    "productUrl": "https://www.coupang.com/vp/products/9358055613?itemId=11747641885&vendorItemId=78681795432&q=%ED%95%98%EA%B8%B0%EC%8A%A4%20%EB%A7%A5%EC%8A%A4%EB%93%9C%EB%9D%BC%EC%9D%B4%20%ED%8C%AC%ED%8B%B0%204%EB%8B%A8%EA%B3%84&searchId=7e8f4b708865965&sourceType=search&itemsCount=72&searchRank=27&rank=27"
  },
  {
    "productId": 9370895090,
    "productName": "2024 맥스드라이 팬티 기저귀 4단계 남아 52x2팩, 2매",
    "productPrice": 177140,
    "productImage": "https://thumbnail.coupangcdn.com/thumbnails/remote/657x657q90trim/image/vendor_inventory/b8d4/8a5ca4b11e6d62f17864fe4fc0e91b8e19fec848f5fed9bf863097a30c50.jpg",
    "productUrl": "https://www.coupang.com/vp/products/9370895090?itemId=27833487651&vendorItemId=94793029087&q=%ED%95%98%EA%B8%B0%EC%8A%A4%20%EB%A7%A5%EC%8A%A4%EB%93%9C%EB%9D%BC%EC%9D%B4%20%ED%8C%AC%ED%8B%B0%204%EB%8B%A8%EA%B3%84&searchId=7e8f4b708865965&sourceType=search&itemsCount=72&searchRank=32&rank=32"
  },
  {
    "productId": 8291762228,
    "productName": "하기스 2021 맥스드라이 팬티형 기저귀 여아용 대형 4단계(9~13kg), 4단계, 90매",
    "productPrice": 99900,
    "productImage": "https://thumbnail.coupangcdn.com/thumbnails/remote/657x657q90trim/image/vendor_inventory/88bc/c3aa18e813975dd23829f84c1f6807438920830a8d11abe70fd0be1d58a2.jpg",
    "productUrl": "https://www.coupang.com/vp/products/8291762228?itemId=12462663479&vendorItemId=79091913538&q=%ED%95%98%EA%B8%B0%EC%8A%A4%20%EB%A7%A5%EC%8A%A4%EB%93%9C%EB%9D%BC%EC%9D%B4%20%ED%8C%AC%ED%8B%B0%204%EB%8B%A8%EA%B3%84&searchId=7e8f4b708865965&sourceType=search&itemsCount=72&searchRank=42&rank=42"
  },
  {
    "productId": 9224451059,
    "productName": "2025년형 하기스 맥스드라이 팬티형 기저귀 4팩 남아, 4단계",
    "productPrice": 109900,
    "productImage": "https://thumbnail.coupangcdn.com/thumbnails/remote/657x657q90trim/image/vendor_inventory/3592/49ac4357711632b82c6944ba09f6036e1bc1c4de2212548c2b1f72301f63.png",
    "productUrl": "https://www.coupang.com/vp/products/9224451059?itemId=26433573266&vendorItemId=93137897470&q=%ED%95%98%EA%B8%B0%EC%8A%A4%20%EB%A7%A5%EC%8A%A4%EB%93%9C%EB%9D%BC%EC%9D%B4%20%ED%8C%AC%ED%8B%B0%204%EB%8B%A8%EA%B3%84&searchId=7e8f4b708865965&sourceType=search&itemsCount=72&searchRank=45&rank=45"
  },
  {
    "productId": 8414440515,
    "productName": "new 하기스 맥스드라이 팬티형 기저귀 4팩 여아용, 4단계, 208매",
    "productPrice": 103410,
    "productImage": "https://thumbnail.coupangcdn.com/thumbnails/remote/657x657q90trim/image/vendor_inventory/3592/49ac4357711632b82c6944ba09f6036e1bc1c4de2212548c2b1f72301f63.png",
    "productUrl": "https://www.coupang.com/vp/products/8414440515?itemId=26433573372&vendorItemId=93137992243&q=%ED%95%98%EA%B8%B0%EC%8A%A4%20%EB%A7%A5%EC%8A%A4%EB%93%9C%EB%9D%BC%EC%9D%B4%20%ED%8C%AC%ED%8B%B0%204%EB%8B%A8%EA%B3%84&searchId=7e8f4b708865965&sourceType=search&itemsCount=72&searchRank=46&rank=46"
  },
  {
    "productId": 9396246786,
    "productName": "2024 하기스기저귀 맥스드라이 4단계 팬티형 여아용 52매x2팩 대형 아기기저귀, 104매",
    "productPrice": 220200,
    "productImage": "https://thumbnail.coupangcdn.com/thumbnails/remote/657x657q90trim/image/vendor_inventory/89f5/5bfd4f07c90ed8d587c58b8231c5634577d544798219303965642ce46015.jpg",
    "productUrl": "https://www.coupang.com/vp/products/9396246786?itemId=27617460661&vendorItemId=94793118677&q=%ED%95%98%EA%B8%B0%EC%8A%A4%20%EB%A7%A5%EC%8A%A4%EB%93%9C%EB%9D%BC%EC%9D%B4%20%ED%8C%AC%ED%8B%B0%204%EB%8B%A8%EA%B3%84&searchId=7e8f4b708865965&sourceType=search&itemsCount=72&searchRank=51&rank=51"
  },
  {
    "productId": 9334783431,
    "productName": "2025 맥스드라이 (팬티형) 4단계 남아 (52매X4팩) 대형 하기스 기저귀",
    "productPrice": 159300,
    "productImage": "https://thumbnail.coupangcdn.com/thumbnails/remote/657x657q90trim/image/vendor_inventory/e63e/c6e3b6eecf9ad0a834f53011b7901243ebb87e485b6b9f5a05cd5d94a318.png",
    "productUrl": "https://www.coupang.com/vp/products/9334783431?itemId=26939205522&vendorItemId=94364180604&q=%ED%95%98%EA%B8%B0%EC%8A%A4%20%EB%A7%A5%EC%8A%A4%EB%93%9C%EB%9D%BC%EC%9D%B4%20%ED%8C%AC%ED%8B%B0%204%EB%8B%A8%EA%B3%84&searchId=7e8f4b708865965&sourceType=search&itemsCount=72&searchRank=65&rank=65"
  },
  {
    "productId": 8359638409,
    "productName": "하기스 맥스드라이 에어팬티 4단계 대형 공용 48매 4팩 / 25년형 신제품, 192매",
    "productPrice": 319040,
    "productImage": "https://thumbnail.coupangcdn.com/thumbnails/remote/657x657q90trim/image/vendor_inventory/a23d/b8acd1d57d72f1f6db56901d0a21dcf9adc9a25e1184323d540366b1a6db.jpg",
    "productUrl": "https://www.coupang.com/vp/products/8359638409?itemId=27617469872&vendorItemId=94793210887&q=%ED%95%98%EA%B8%B0%EC%8A%A4%20%EB%A7%A5%EC%8A%A4%EB%93%9C%EB%9D%BC%EC%9D%B4%20%ED%8C%AC%ED%8B%B0%204%EB%8B%A8%EA%B3%84&searchId=7e8f4b708865965&sourceType=search&itemsCount=72&searchRank=66&rank=66"
  },
  {
    "productId": 7881685402,
    "productName": "하기스 네이처메이드 밤부 팬티형 기저귀 남여공용 대형, 4단계, 84매",
    "productPrice": 56900,
    "productImage": "https://thumbnail.coupangcdn.com/thumbnails/remote/292x292ex/image/retail/images/2025/09/02/15/7/62b4fb25-e08e-468f-b88d-0c5ae776b52c.png",
    "productUrl": "https://www.coupang.com/vp/products/7881685402?vendorItemId=93478679306&sourceType=srp_also_viewed_item&rmdId=4ac32c485ec74985a2f2ebd05df04c15&eventLabel=recommendation_widget_pc_srp_001&platform=web&rmdABTestInfo=88611_A,14554_C,88610_B&rmdValue=p8065577198:vt-1.0.0:p7881685402"
  },
  {
    "productId": 8449829217,
    "productName": "하기스 뉴 보송보송 팬티형 기저귀 공용, 7단계, 68매",
    "productPrice": 40900,
    "productImage": "https://thumbnail.coupangcdn.com/thumbnails/remote/292x292ex/image/retail/images/1140316945399605-6c7b6b5f-c1ab-412c-87ae-2c6b8d22e39c.jpg",
    "productUrl": "https://www.coupang.com/vp/products/8449829217?vendorItemId=80676448301&sourceType=srp_also_viewed_item&rmdId=4ac32c485ec74985a2f2ebd05df04c15&eventLabel=recommendation_widget_pc_srp_001&platform=web&rmdABTestInfo=88611_A,14554_C,88610_B&rmdValue=p8065577198:vt-1.0.0:p8449829217"
  },
  {
    "productId": 8750398261,
    "productName": "하기스 맥스드라이 에어 밴드형 기저귀 아동용, 3단계, 128매",
    "productPrice": 49800,
    "productImage": "https://thumbnail.coupangcdn.com/thumbnails/remote/292x292ex/image/retail/images/2025/03/07/11/4/79a87cfe-739b-4b31-9d0c-808a4451b884.png",
    "productUrl": "https://www.coupang.com/vp/products/8750398261?vendorItemId=92059836915&sourceType=srp_also_viewed_item&rmdId=4ac32c485ec74985a2f2ebd05df04c15&eventLabel=recommendation_widget_pc_srp_001&platform=web&rmdABTestInfo=88611_A,14554_C,88610_B&rmdValue=p8065577198:vt-1.0.0:p8750398261"
  },
  {
    "productId": 7867859869,
    "productName": "하기스 2024 네이처메이드밤부 팬티형 기저귀 여아용 점보 1팩, 6단계, 38매",
    "productPrice": 30000,
    "productImage": "https://thumbnail.coupangcdn.com/thumbnails/remote/292x292ex/image/vendor_inventory/14f0/ba6dd4bc37051e0a68a532af3271f9427b676d2fad72fafe63b703ce0eda.jpg",
    "productUrl": "https://www.coupang.com/vp/products/7867859869?vendorItemId=92591895049&sourceType=srp_also_viewed_item&rmdId=4ac32c485ec74985a2f2ebd05df04c15&eventLabel=recommendation_widget_pc_srp_001&platform=web&rmdABTestInfo=88611_A,14554_C,88610_B&rmdValue=p8065577198:vt-1.0.0:p7867859869"
  },
  {
    "productId": 8817458265,
    "productName": "하기스 2023 매직컴포트썸머 특대형 5단계(11~16kg) 팬티형 기저귀 남여공용, 7단계, 34매",
    "productPrice": 34500,
    "productImage": "https://thumbnail.coupangcdn.com/thumbnails/remote/292x292ex/image/vendor_inventory/9605/cec2c3d0e86ec10d39b749dcca847d6eddbcddf77c7c02e1726eb605c40a.png",
    "productUrl": "https://www.coupang.com/vp/products/8817458265?vendorItemId=92500105433&sourceType=srp_also_viewed_item&rmdId=4ac32c485ec74985a2f2ebd05df04c15&eventLabel=recommendation_widget_pc_srp_001&platform=web&rmdABTestInfo=88611_A,14554_C,88610_B&rmdValue=p8065577198:vt-1.0.0:p8817458265"
  },
  {
    "productId": 7927695825,
    "productName": "하기스 NEW 맥스드라이 밴드형 남여공용, 2단계, 58개",
    "productPrice": 25000,
    "productImage": "https://thumbnail.coupangcdn.com/thumbnails/remote/292x292ex/image/vendor_inventory/a242/4d7ab81205e4b03a7ea38460ad0a09f577ce473515791c710c37c52a21f8.jpg",
    "productUrl": "https://www.coupang.com/vp/products/7927695825?vendorItemId=88949631079&sourceType=srp_also_viewed_item&rmdId=4ac32c485ec74985a2f2ebd05df04c15&eventLabel=recommendation_widget_pc_srp_001&platform=web&rmdABTestInfo=88611_A,14554_C,88610_B&rmdValue=p8065577198:vt-1.0.0:p7927695825"
  },
  {
    "productId": 9319755634,
    "productName": "하기스 2026 매직컴포트 팬티형 기저귀 남아용, 7단계, 64매",
    "productPrice": 48220,
    "productImage": "https://thumbnail.coupangcdn.com/thumbnails/remote/292x292ex/image/retail/images/2026/01/19/18/8/cf3dd06a-00d8-4b8c-9a7a-68ee8c2e7577.jpg",
    "productUrl": "https://www.coupang.com/vp/products/9319755634?vendorItemId=94579119330&sourceType=srp_also_viewed_item&rmdId=4ac32c485ec74985a2f2ebd05df04c15&eventLabel=recommendation_widget_pc_srp_001&platform=web&rmdABTestInfo=88611_A,14554_C,88610_B&rmdValue=p8065577198:vt-1.0.0:p9319755634"
  },
  {
    "productId": 7956680597,
    "productName": "하기스 2024 매직컴포트 팬티형 기저귀 남녀공용, 6단계, 72매",
    "productPrice": 41900,
    "productImage": "https://thumbnail.coupangcdn.com/thumbnails/remote/292x292ex/image/retail/images/690302295310304-4061cbf5-98ba-4543-ba10-eca6d8c2995f.jpg",
    "productUrl": "https://www.coupang.com/vp/products/7956680597?vendorItemId=89031970705&sourceType=srp_also_viewed_item&rmdId=4ac32c485ec74985a2f2ebd05df04c15&eventLabel=recommendation_widget_pc_srp_001&platform=web&rmdABTestInfo=88611_A,14554_C,88610_B&rmdValue=p8065577198:vt-1.0.0:p7956680597"
  },
  {
    "productId": 9150924970,
    "productName": "팸퍼스 2026 엔젤브리즈 소프트 팬티형 기저귀 남여공용, 6단계, 120매",
    "productPrice": 72100,
    "productImage": "https://thumbnail.coupangcdn.com/thumbnails/remote/292x292ex/image/retail/images/5849680464789-ba57ba01-871f-4e3d-a034-a49fe0bf2528.jpg",
    "productUrl": "https://www.coupang.com/vp/products/9150924970?vendorItemId=93914985933&sourceType=srp_also_viewed_item&rmdId=4ac32c485ec74985a2f2ebd05df04c15&eventLabel=recommendation_widget_pc_srp_001&platform=web&rmdABTestInfo=88611_A,14554_C,88610_B&rmdValue=p8065577198:vt-1.0.0:p9150924970"
  },
  {
    "productId": 8750126776,
    "productName": "하기스 NEW 맥스드라이 여아용 팬티형 기저귀, 88개, 5단계",
    "productPrice": 63000,
    "productImage": "https://thumbnail.coupangcdn.com/thumbnails/remote/292x292ex/image/vendor_inventory/2f3a/84f6d163899042e4dc88b81eb300ba56c93fefe19171666a0ac974eacac3.png",
    "productUrl": "https://www.coupang.com/vp/products/8750126776?vendorItemId=94588444463&sourceType=srp_also_viewed_item&rmdId=4ac32c485ec74985a2f2ebd05df04c15&eventLabel=recommendation_widget_pc_srp_001&platform=web&rmdABTestInfo=88611_A,14554_C,88610_B&rmdValue=p8065577198:vt-1.0.0:p8750126776"
  },
  {
    "productId": 8533699348,
    "productName": "팸퍼스 통잠 팬티형 기저귀 아동용, 5단계, 104매",
    "productPrice": 50970,
    "productImage": "https://thumbnail.coupangcdn.com/thumbnails/remote/292x292ex/image/vendor_inventory/image_audit/prod/cf7f452b-a088-4858-ba79-3422376c934c_fixing_v2.png",
    "productUrl": "https://www.coupang.com/vp/products/8533699348?vendorItemId=91712149812&sourceType=srp_also_viewed_item&rmdId=4ac32c485ec74985a2f2ebd05df04c15&eventLabel=recommendation_widget_pc_srp_001&platform=web&rmdABTestInfo=88611_A,14554_C,88610_B&rmdValue=p8065577198:vt-1.0.0:p8533699348"
  },
  {
    "productId": 9055590053,
    "productName": "하기스 네이처메이드 밤부 팬티형 기저귀 남아용 대형, 4단계, 108매",
    "productPrice": 57900,
    "productImage": "https://thumbnail.coupangcdn.com/thumbnails/remote/292x292ex/image/retail/images/2025/09/02/15/8/e38547d3-b62a-4510-b547-8025ef97c615.png",
    "productUrl": "https://www.coupang.com/vp/products/9055590053?vendorItemId=93478679236&sourceType=srp_also_viewed_item&rmdId=4ac32c485ec74985a2f2ebd05df04c15&eventLabel=recommendation_widget_pc_srp_001&platform=web&rmdABTestInfo=88611_A,14554_C,88610_B&rmdValue=p8065577198:vt-1.0.0:p9055590053"
  },
  {
    "productId": 9046757137,
    "productName": "하기스 맥스드라이 밴드형 기저귀 남녀공용 중형, 3단계, 144매",
    "productPrice": 50610,
    "productImage": "https://thumbnail.coupangcdn.com/thumbnails/remote/292x292ex/image/retail/images/2025/09/08/10/4/97b86bb5-9a98-44ea-9390-e4c641806402.png",
    "productUrl": "https://www.coupang.com/vp/products/9046757137?vendorItemId=93525063587&sourceType=srp_also_viewed_item&rmdId=4ac32c485ec74985a2f2ebd05df04c15&eventLabel=recommendation_widget_pc_srp_001&platform=web&rmdABTestInfo=88611_A,14554_C,88610_B&rmdValue=p8065577198:vt-1.0.0:p9046757137"
  }
]
